{
  "project_info": {
    "project_number": "600830782953",
    "project_id": "sheltermind-c6ec2",
    "storage_bucket": "sheltermind-c6ec2.firebasestorage.app"
  },
  "client": [
    {
      "client_info": {
        "mobilesdk_app_id": "1:600830782953:android:60314a886ab83917912f78",
        "android_client_info": {
          "package_name": "com.ud.myapplication"
        }
      },
      "oauth_client": [],
      "api_key": [
        {
          "current_key": "AIzaSyAGK_5VTnZIjXcgnu1ijaUZGr16DuGBB3M"
        }
      ],
      "services": {
        "appinvite_service": {
          "other_platform_oauth_client": []
        }
      }
    }
  ],
  "configuration_version": "1"
}